json_default.py
json_default-0.2.dist-info/DESCRIPTION.rst
json_default-0.2.dist-info/METADATA
json_default-0.2.dist-info/RECORD
json_default-0.2.dist-info/WHEEL
json_default-0.2.dist-info/metadata.json
json_default-0.2.dist-info/top_level.txt
