Metadata-Version: 2.0
Name: json-default
Version: 0.2
Summary: Extensible default function for JSONEncoder
Home-page: https://github.com/funkybob/json_default
Author: Curtis Maloney
Author-email: curtis@tinbrain.net
License: MIT
Platform: UNKNOWN
Classifier: License :: OSI Approved :: MIT License
Classifier: Programming Language :: Python
Classifier: Programming Language :: Python :: 3
Classifier: Programming Language :: Python :: 3.4
Classifier: Programming Language :: Python :: 3.5
Classifier: Programming Language :: Python :: 3.6
Classifier: Programming Language :: Python :: Implementation :: CPython
Classifier: Programming Language :: Python :: Implementation :: PyPy
